PyFWI/__init__.py
PyFWI/acquisition.py
PyFWI/elastic.cl
PyFWI/elastic_crosswell.cl
PyFWI/elastic_surface.cl
PyFWI/fwi.py
PyFWI/fwi_tools.py
PyFWI/grad_switcher.py
PyFWI/model_dataset.py
PyFWI/optimization.py
PyFWI/processing.py
PyFWI/rock_physics.py
PyFWI/seiplot.py
PyFWI/seismic_io.py
PyFWI/tl_fwi.py
PyFWI/torchfwi.py
PyFWI/version.py
PyFWI/wave_propagation.py
PyFWI-0.1.10.dist-info/LICENSE
PyFWI-0.1.10.dist-info/METADATA
PyFWI-0.1.10.dist-info/WHEEL
PyFWI-0.1.10.dist-info/top_level.txt
PyFWI-0.1.10.dist-info/RECORD
