Metadata-Version: 2.1
Name: PyFWI
Version: 0.1.10
Summary: PyFWI is a Pyhton package for seismic FWI and reservoir monitoring
Home-page: https://github.com/AmirMardan/PyFWI
Author: Amir Mardan
Author-email: mardan.amir.h@gmail.com
Project-URL: Bug Tracker, https://github.com/AmirMardan/PyFWI/issues
Classifier: Intended Audience :: Education
Classifier: Programming Language :: C
Classifier: Programming Language :: Python :: 3.7
Classifier: Programming Language :: Python :: 3.10
Classifier: License :: OSI Approved :: GNU General Public License v3 or later (GPLv3+)
Classifier: Operating System :: OS Independent
Classifier: Operating System :: Microsoft :: Windows
Classifier: Intended Audience :: Education
Classifier: Intended Audience :: Science/Research
Requires-Python: >=3.7
License-File: LICENSE
Requires-Dist: setuptools>=42
Requires-Dist: wheel
Requires-Dist: numpy
Requires-Dist: matplotlib
Requires-Dist: scipy
Requires-Dist: hdf5storage
Requires-Dist: requests
Requires-Dist: datetime
